README.md
setup.py
Epip.egg-info/PKG-INFO
Epip.egg-info/SOURCES.txt
Epip.egg-info/dependency_links.txt
Epip.egg-info/not-zip-safe
Epip.egg-info/top_level.txt
epip/__init__.py
epip/pipe.py