Metadata-Version: 1.1
Name: Epip
Version: 1.0.2
Summary: Pipe style programming in Python
Home-page: https://github.com/yadizhou/epip
Author: Yadi Zhou
Author-email: yadizhou90@gmail.com
License: MIT
Keywords: pipeline pipe infix functional
Platform: UNKNOWN
Classifier: Development Status :: 4 - Beta
Classifier: Environment :: Win32 (MS Windows)
Classifier: Environment :: X11 Applications :: GTK
Classifier: Environment :: MacOS X :: Cocoa
Classifier: Operating System :: Microsoft :: Windows :: Windows 10
Classifier: Operating System :: Microsoft :: Windows :: Windows 7
Classifier: Operating System :: POSIX :: Linux
Classifier: Operating System :: MacOS :: MacOS X
Classifier: Intended Audience :: Developers
Classifier: Intended Audience :: Education
Classifier: Intended Audience :: End Users/Desktop
Classifier: Intended Audience :: Science/Research
Classifier: Topic :: Education
Classifier: Programming Language :: Python :: 3.5
Classifier: Programming Language :: Python :: 3.6
